{"trial_id": "0051", "hyperparameters": {"space": [{"class_name": "Int", "config": {"name": "hidden_layers", "default": null, "conditions": [], "min_value": 1, "max_value": 5, "step": 1, "sampling": "linear"}}, {"class_name": "Int", "config": {"name": "neurons", "default": null, "conditions": [], "min_value": 1, "max_value": 100, "step": 1, "sampling": "linear"}}, {"class_name": "Float", "config": {"name": "learning_rate", "default": 0.0001, "conditions": [], "min_value": 0.0001, "max_value": 0.01, "step": null, "sampling": "log"}}, {"class_name": "Float", "config": {"name": "l2", "default": 0.0001, "conditions": [], "min_value": 0.0001, "max_value": 100.0, "step": null, "sampling": "log"}}, {"class_name": "Choice", "config": {"name": "optimizer", "default": "SGD", "conditions": [], "values": ["SGD", "Nadam"], "ordered": false}}], "values": {"hidden_layers": 3, "neurons": 22, "learning_rate": 0.0015228263940738605, "l2": 0.006478068107246733, "optimizer": "Nadam", "tuner/epochs": 30, "tuner/initial_epoch": 10, "tuner/bracket": 3, "tuner/round": 3, "tuner/trial_id": "0046"}}, "metrics": {"metrics": {"loss": {"direction": "min", "observations": [{"value": [5.102239608764648], "step": 19}]}, "val_loss": {"direction": "min", "observations": [{"value": [0.968397855758667], "step": 19}]}}}, "score": 0.968397855758667, "best_step": 19, "status": "COMPLETED", "message": null}